setup.py
pev/__init__.py
pev.egg-info/PKG-INFO
pev.egg-info/SOURCES.txt
pev.egg-info/dependency_links.txt
pev.egg-info/top_level.txt