Metadata-Version: 1.1
Name: pev
Version: 0.1.0
Summary: Python EVenter library
Home-page: https://github.com/stanislavfeldman/pev
Author: Stanislav Feldman
Author-email: UNKNOWN
License: UNKNOWN
Keywords: eventer pubsub publish subscribe
Platform: UNKNOWN
Classifier: Topic :: Software Development
